diskimage_builder/__init__.py
diskimage_builder/disk_image_create.py
diskimage_builder/diskimage_builder.py
diskimage_builder/element_dependencies.py
diskimage_builder/logging_config.py
diskimage_builder/paths.py
diskimage_builder/version.py
diskimage_builder/block_device/__init__.py
diskimage_builder/block_device/blockdevice.py
diskimage_builder/block_device/cmd.py
diskimage_builder/block_device/config.py
diskimage_builder/block_device/exception.py
diskimage_builder/block_device/plugin.py
diskimage_builder/block_device/utils.py
diskimage_builder/block_device/level0/__init__.py
diskimage_builder/block_device/level0/localloop.py
diskimage_builder/block_device/level1/__init__.py
diskimage_builder/block_device/level1/lvm.py
diskimage_builder/block_device/level1/mbr.py
diskimage_builder/block_device/level1/partition.py
diskimage_builder/block_device/level1/partitioning.py
diskimage_builder/block_device/level2/__init__.py
diskimage_builder/block_device/level2/mkfs.py
diskimage_builder/block_device/level3/__init__.py
diskimage_builder/block_device/level3/mount.py
diskimage_builder/block_device/level4/__init__.py
diskimage_builder/block_device/level4/fstab.py
diskimage_builder/block_device/tests/__init__.py
diskimage_builder/block_device/tests/test_base.py
diskimage_builder/block_device/tests/test_config.py
diskimage_builder/block_device/tests/test_gpt.py
diskimage_builder/block_device/tests/test_lvm.py
diskimage_builder/block_device/tests/test_mbr.py
diskimage_builder/block_device/tests/test_mkfs.py
diskimage_builder/block_device/tests/test_mount_order.py
diskimage_builder/block_device/tests/test_state.py
diskimage_builder/block_device/tests/test_utils.py
diskimage_builder/block_device/tests/config/bad_edge_graph.yaml
diskimage_builder/block_device/tests/config/bad_plugin.yaml
diskimage_builder/block_device/tests/config/cmd_create.yaml
diskimage_builder/block_device/tests/config/deep_graph.yaml
diskimage_builder/block_device/tests/config/deep_tree.yaml
diskimage_builder-3.40.2.dist-info/licenses/AUTHORS
diskimage_builder-3.40.2.dist-info/licenses/LICENSE
diskimage_builder-3.40.2.dist-info/METADATA
diskimage_builder-3.40.2.dist-info/WHEEL
diskimage_builder-3.40.2.dist-info/entry_points.txt
diskimage_builder-3.40.2.dist-info/pbr.json
diskimage_builder-3.40.2.dist-info/top_level.txt
diskimage_builder-3.40.2.dist-info/RECORD
