Metadata-Version: 2.4
Name: diskimage-builder
Version: 3.40.2
Summary: Golden Disk Image builder.
Home-page: https://docs.openstack.org/diskimage-builder/latest/
Author: OpenStack
Author-email: openstack-discuss@lists.openstack.org
License: Apache License (2.0)
Classifier: Development Status :: 5 - Production/Stable
Classifier: License :: OSI Approved :: Apache Software License
Classifier: Operating System :: POSIX :: Linux
Classifier: Programming Language :: Python :: 3
Classifier: Programming Language :: Python :: 3.6
Classifier: Programming Language :: Python :: 3.7
Classifier: Programming Language :: Python :: 3.8
Classifier: Programming Language :: Python :: 3.9
Classifier: Programming Language :: Python :: 3.10
Classifier: Environment :: Console
Requires-Python: >=3.6
License-File: LICENSE
License-File: AUTHORS
Requires-Dist: networkx>=2.3.0
Requires-Dist: pbr!=2.1.0,>=2.0.0
Requires-Dist: PyYAML>=3.12
Requires-Dist: stevedore>=1.20.0
Requires-Dist: flake8<7.0.0,>=3.6.0
Requires-Dist: jsonschema>=3.0.2
Dynamic: author
Dynamic: author-email
Dynamic: classifier
Dynamic: description
Dynamic: home-page
Dynamic: license
Dynamic: license-file
Dynamic: requires-dist
Dynamic: requires-python
Dynamic: summary
